videosdk/plugins/rnnoise/__init__.py
videosdk/plugins/rnnoise/build_rnnoise.py
videosdk/plugins/rnnoise/denoise.py
videosdk/plugins/rnnoise/rnnoise.py
videosdk/plugins/rnnoise/version.py
videosdk/plugins/rnnoise/files/librnnoise.0.dylib
videosdk/plugins/rnnoise/files/librnnoise.dylib
videosdk_plugins_rnnoise-0.0.58.dist-info/METADATA
videosdk_plugins_rnnoise-0.0.58.dist-info/WHEEL
videosdk_plugins_rnnoise-0.0.58.dist-info/RECORD
